modelicares/__init__.py
modelicares/_freqplot.py
modelicares/_gui.py
modelicares/_res.py
modelicares/linres.py
modelicares/simres.py
modelicares/texunit.py
modelicares/util.py
modelicares/_io/__init__.py
modelicares/_io/dymola.py
modelicares/exps/__init__.py
modelicares/exps/doe.py
Modelicares_Revised-1.0.dist-info/LICENSE.txt
Modelicares_Revised-1.0.dist-info/METADATA
Modelicares_Revised-1.0.dist-info/WHEEL
Modelicares_Revised-1.0.dist-info/top_level.txt
Modelicares_Revised-1.0.dist-info/RECORD
