Metadata-Version: 2.1
Name: Modelicares-Revised
Version: 1.0
Summary: Change hyper-parameters in dsin.txt file derived from Dymola
Home-page: UNKNOWN
Author: Kevin Davies and Sun Yeqi
Author-email: yeqi_sun@163.com
License: UNKNOWN
Platform: UNKNOWN
Classifier: Programming Language :: Python :: 3
Classifier: License :: OSI Approved :: MIT License
Classifier: Operating System :: OS Independent
Requires-Python: >=3.6
License-File: LICENSE.txt
